{"dependencies":[{"name":"/Users/cecile.lesgourgues/Documents/gif-paradise/.babelrc","includedInParent":true,"mtime":1518771265119}],"generated":{"js":"\"use strict\";\n\nObject.defineProperty(exports, \"__esModule\", {\n    value: true\n});\nvar on = function on(target, event, handler) {\n    return target.addEventListener(event, handler);\n};\n\nexports.on = on;","map":{"mappings":[{"generated":{"line":6,"column":0},"source":"src/js/helpers/events.js","original":{"line":1,"column":0}},{"name":"on","generated":{"line":6,"column":4},"source":"src/js/helpers/events.js","original":{"line":1,"column":6}},{"generated":{"line":6,"column":9},"source":"src/js/helpers/events.js","original":{"line":1,"column":11}},{"name":"on","generated":{"line":6,"column":18},"source":"src/js/helpers/events.js","original":{"line":1,"column":6}},{"generated":{"line":6,"column":20},"source":"src/js/helpers/events.js","original":{"line":1,"column":11}},{"name":"target","generated":{"line":6,"column":21},"source":"src/js/helpers/events.js","original":{"line":1,"column":12}},{"generated":{"line":6,"column":27},"source":"src/js/helpers/events.js","original":{"line":1,"column":11}},{"name":"event","generated":{"line":6,"column":29},"source":"src/js/helpers/events.js","original":{"line":1,"column":20}},{"generated":{"line":6,"column":34},"source":"src/js/helpers/events.js","original":{"line":1,"column":11}},{"name":"handler","generated":{"line":6,"column":36},"source":"src/js/helpers/events.js","original":{"line":1,"column":27}},{"generated":{"line":6,"column":43},"source":"src/js/helpers/events.js","original":{"line":1,"column":11}},{"generated":{"line":6,"column":45},"source":"src/js/helpers/events.js","original":{"line":1,"column":39}},{"generated":{"line":7,"column":0},"source":"src/js/helpers/events.js","original":{"line":2,"column":4}},{"name":"target","generated":{"line":7,"column":11},"source":"src/js/helpers/events.js","original":{"line":2,"column":11}},{"name":"addEventListener","generated":{"line":7,"column":18},"source":"src/js/helpers/events.js","original":{"line":2,"column":18}},{"generated":{"line":7,"column":34},"source":"src/js/helpers/events.js","original":{"line":2,"column":11}},{"name":"event","generated":{"line":7,"column":35},"source":"src/js/helpers/events.js","original":{"line":2,"column":35}},{"generated":{"line":7,"column":40},"source":"src/js/helpers/events.js","original":{"line":2,"column":11}},{"name":"handler","generated":{"line":7,"column":42},"source":"src/js/helpers/events.js","original":{"line":2,"column":42}},{"generated":{"line":7,"column":49},"source":"src/js/helpers/events.js","original":{"line":2,"column":11}},{"generated":{"line":7,"column":50},"source":"src/js/helpers/events.js","original":{"line":2,"column":4}},{"generated":{"line":8,"column":0},"source":"src/js/helpers/events.js","original":{"line":3,"column":3}},{"generated":{"line":8,"column":1},"source":"src/js/helpers/events.js","original":{"line":1,"column":0}},{"name":"on","generated":{"line":10,"column":8},"source":"src/js/helpers/events.js","original":{"line":5,"column":11}},{"name":"on","generated":{"line":10,"column":13},"source":"src/js/helpers/events.js","original":{"line":5,"column":11}}],"sources":{"src/js/helpers/events.js":"const on = (target, event, handler) => {\n    return target.addEventListener(event, handler);\n  };\n  \n  export { on };"},"lineCount":null}},"hash":"e327ccf9ca57e9eba24d4e0ade1e057c","cacheData":{"env":{}}}